pyself-1.0.0.dist-info/METADATA
pyself-1.0.0.dist-info/WHEEL
pyself-1.0.0.dist-info/licenses/LICENSE
pyself/__init__.py
pyself/geometry.py
pyself/lagrange.py
pyself/model1d.py
pyself/model2d.py
pyself-1.0.0.dist-info/RECORD
